TkGifWidget/TkGifWidget.py
TkGifWidget/TkGifWidget.pyi
TkGifWidget/__init__.py
TkGifWidget/py.typed
tkgifwidget-0.0.9.dist-info/licenses/LICENSE
tkgifwidget-0.0.9.dist-info/METADATA
tkgifwidget-0.0.9.dist-info/WHEEL
tkgifwidget-0.0.9.dist-info/top_level.txt
tkgifwidget-0.0.9.dist-info/RECORD
