Metadata-Version: 2.4
Name: TkGifWidget
Version: 0.0.9
Summary: A widget that displays GIFs in Tkinter
Author: JellyfisHawthorn
Project-URL: Homepage, https://github.com/JellyfisHawthorn/TkGifWidgit
Project-URL: Issues, https://github.com/JellyfisHawthorn/TkGifWidgit/issues
Project-URL: Changelog, https://github.com/JellyfisHawthorn/TkGifWidget/blob/main/CHANGELOG.md
Keywords: tkinter,gif,widget,Animated
Classifier: Programming Language :: Python :: 3
Classifier: Operating System :: OS Independent
Classifier: License :: Public Domain
Requires-Python: >=3.8
License-File: LICENSE
Requires-Dist: pillow
Dynamic: license-file
